django_cosmograph/__init__.py
django_cosmograph/admin.py
django_cosmograph/apps.py
django_cosmograph/models.py
django_cosmograph/tests.py
django_cosmograph/urls.py
django_cosmograph/utils.py
django_cosmograph/views.py
django_cosmograph/migrations/__init__.py
django_cosmograph/static/django_cosmograph/cosmograph.js
django_cosmograph/templates/django_cosmograph/cosmograph.html
django_cosmograph/templates/django_cosmograph/cosmograph_partial.html
django_cosmograph-0.3.11.dist-info/METADATA
django_cosmograph-0.3.11.dist-info/WHEEL
django_cosmograph-0.3.11.dist-info/licenses/LICENSE.md
django_cosmograph-0.3.11.dist-info/RECORD
