Metadata-Version: 2.4
Name: django-cosmograph
Version: 0.3.11
Summary: A django app to get cosmograph visualisations directly in django templates
Author-email: Saranya Balasubramanian <saranya.balasubramanian@oeaw.ac.at>
License-File: LICENSE.md
Requires-Python: >=3.11
Requires-Dist: django<6,>=4.2
Requires-Dist: matplotlib>=3.10.3
Requires-Dist: seaborn>=0.13.2
